playcric/__init__.py
playcric/alleyn.py
playcric/config.py
playcric/playcricket.py
playcric/utils.py
pyplaycricket-1.3.2.dist-info/LICENSE
pyplaycricket-1.3.2.dist-info/METADATA
pyplaycricket-1.3.2.dist-info/WHEEL
pyplaycricket-1.3.2.dist-info/top_level.txt
pyplaycricket-1.3.2.dist-info/RECORD
