Metadata-Version: 2.1
Name: pyplaycricket
Version: 1.3.2
Summary: Iteracting with the playcricket API for statistical analysis and automated social media posts.
Home-page: https://github.com/ewanharris12/pyplaycricket
Author: Ewan Harris
License-File: LICENSE
Requires-Dist: numpy==1.24.4
Requires-Dist: pandas==2.0.3
Requires-Dist: requests==2.27.1
